diii/__init__.py
diii/cli.py
diii/exceptions.py
diii/iii.py
diii/repl.py
diii/server.py
monome_diii-1.0.1.dist-info/LICENSE
monome_diii-1.0.1.dist-info/METADATA
monome_diii-1.0.1.dist-info/WHEEL
monome_diii-1.0.1.dist-info/entry_points.txt
monome_diii-1.0.1.dist-info/top_level.txt
monome_diii-1.0.1.dist-info/RECORD
