Metadata-Version: 2.1
Name: monome-diii
Version: 1.0.1
Summary: Terminal interface for iii devices
Home-page: https://github.com/monome/diii
Author: monome
Author-email: bcrabtree@monome.org
Classifier: Programming Language :: Python :: 3
Classifier: License :: OSI Approved :: GNU General Public License v3 (GPLv3)
Classifier: Operating System :: OS Independent
Requires-Python: >=3.6
License-File: LICENSE
Requires-Dist: Click>=7.0
Requires-Dist: packaging
Requires-Dist: prompt-toolkit<3.0,>=2.0.10
Requires-Dist: pyserial>=3.4
Requires-Dist: pyusb
Requires-Dist: requests
Requires-Dist: websockets>=9.1
Requires-Dist: setuptools
Requires-Dist: setuptools-scm
Requires-Dist: setuptools-scm-git-archive
Provides-Extra: test
Requires-Dist: pylint; extra == "test"
